turbo_alignment/__init__.py
turbo_alignment/__main__.py
turbo_alignment/cherry_picks/__init__.py
turbo_alignment/cherry_picks/base.py
turbo_alignment/cherry_picks/chat.py
turbo_alignment/cherry_picks/classification.py
turbo_alignment/cherry_picks/multimodal.py
turbo_alignment/cherry_picks/rag.py
turbo_alignment/cherry_picks/rm.py
turbo_alignment/cli/__init__.py
turbo_alignment/cli/app.py
turbo_alignment/cli/common.py
turbo_alignment/cli/inference.py
turbo_alignment/cli/sampling.py
turbo_alignment/cli/train.py
turbo_alignment/common/__init__.py
turbo_alignment/common/data/__init__.py
turbo_alignment/common/data/io.py
turbo_alignment/common/data/multimodal/__init__.py
turbo_alignment/common/data/multimodal/audio/__init__.py
turbo_alignment/common/data/multimodal/audio/base.py
turbo_alignment/common/data/multimodal/audio/imagebind.py
turbo_alignment/common/data/multimodal/audio/whisper.py
turbo_alignment/common/data/multimodal/base.py
turbo_alignment/common/data/multimodal/common.py
turbo_alignment/common/data/multimodal/image/__init__.py
turbo_alignment/common/data/multimodal/image/base.py
turbo_alignment/common/data/multimodal/image/clip.py
turbo_alignment/common/data/multimodal/image/imagebind.py
turbo_alignment/common/data/multimodal/registry.py
turbo_alignment/common/logging/__init__.py
turbo_alignment/common/logging/logger.py
turbo_alignment/common/logging/weights_and_biases.py
turbo_alignment/common/s3/__init__.py
turbo_alignment/common/s3/checkpoints_handler.py
turbo_alignment/common/singleton.py
turbo_alignment/common/tf/__init__.py
turbo_alignment/common/tf/callbacks/__init__.py
turbo_alignment/common/tf/callbacks/common.py
turbo_alignment/common/tf/callbacks/s3.py
turbo_alignment/common/tf/callbacks/sync_ref_model.py
turbo_alignment/common/tf/callbacks/weights_and_biases.py
turbo_alignment/common/tf/convert_to_base_model.py
turbo_alignment/common/tf/loaders/__init__.py
turbo_alignment/common/tf/loaders/model/__init__.py
turbo_alignment-0.1.0.dist-info/LICENSE
turbo_alignment-0.1.0.dist-info/WHEEL
turbo_alignment-0.1.0.dist-info/METADATA
turbo_alignment-0.1.0.dist-info/RECORD
