Metadata-Version: 2.1
Name: turbo-alignment
Version: 0.1.0
Summary: turbo-alignment repository
Author: T Mega Alignment Team
Author-email: n.surnachev@tcsbank.ru
Requires-Python: >=3.10,<4.0
Classifier: Programming Language :: Python :: 3
Classifier: Programming Language :: Python :: 3.10
Classifier: Programming Language :: Python :: 3.11
Requires-Dist: albumentations (>=1.3.1,<2.0.0)
Requires-Dist: allenai-common (>=1.1.2,<2.0.0)
Requires-Dist: bitsandbytes (>=0.41.1,<0.42.0)
Requires-Dist: datasets (>=2.18.0,<3.0.0)
Requires-Dist: einops (>=0.6.1,<0.7.0)
Requires-Dist: evaluate (>=0.4.1,<0.5.0)
Requires-Dist: ftfy (>=6.1.1,<7.0.0)
Requires-Dist: hvac (>=1.1.1,<2.0.0)
Requires-Dist: iopath (>=0.1.10,<0.2.0)
Requires-Dist: jupyter (>=1.0.0,<2.0.0)
Requires-Dist: langchain-huggingface (>=0.0.3,<0.0.4)
Requires-Dist: loguru (>=0.7.0,<0.8.0)
Requires-Dist: numpy (>=1.21,<2.0)
Requires-Dist: opencv-python (>=4.10.0.84,<5.0.0.0)
Requires-Dist: peft (==0.8.2)
Requires-Dist: platformdirs (>=3.5.3,<4.0.0)
Requires-Dist: protobuf (>=3.20.0,<4.0.0)
Requires-Dist: pydantic (>=2.7.0,<3.0.0)
Requires-Dist: pydantic-settings (>=2.2.1,<3.0.0)
Requires-Dist: python-dotenv (>=1.0.0,<2.0.0)
Requires-Dist: pytorchvideo (>=0.1.5,<0.2.0)
Requires-Dist: ragas (>=0.1.10,<0.2.0)
Requires-Dist: rouge-score (>=0.1.2,<0.2.0)
Requires-Dist: scipy (>=1.1.0,<2.0.0)
Requires-Dist: sentence-transformers (>=2.2.2,<3.0.0)
Requires-Dist: sentencepiece (>=0.1.99,<0.2.0)
Requires-Dist: soundfile (>=0.12.1,<0.13.0)
Requires-Dist: timm (>=0.9.7,<0.10.0)
Requires-Dist: tomlkit (>=0.11.8,<0.12.0)
Requires-Dist: torch (>=2.0.0,<3.0.0)
Requires-Dist: torchaudio (>=2.0.2,<3.0.0)
Requires-Dist: transformers (==4.42.0)
Requires-Dist: typer (>=0.9.0,<0.10.0)
Requires-Dist: wandb (>=0.15.3,<0.16.0)
Requires-Dist: wheel (>=0.42.0,<0.43.0)
